ml_pipeline_engine/__init__.py
ml_pipeline_engine/artifact_store/__init__.py
ml_pipeline_engine/artifact_store/enums.py
ml_pipeline_engine/artifact_store/errors.py
ml_pipeline_engine/artifact_store/serializers.py
ml_pipeline_engine/artifact_store/store/__init__.py
ml_pipeline_engine/artifact_store/store/base.py
ml_pipeline_engine/artifact_store/store/filesystem.py
ml_pipeline_engine/artifact_store/store/no_op.py
ml_pipeline_engine/chart.py
ml_pipeline_engine/const.py
ml_pipeline_engine/context/__init__.py
ml_pipeline_engine/context/dag.py
ml_pipeline_engine/dag/__init__.py
ml_pipeline_engine/dag/dag.py
ml_pipeline_engine/dag/enums.py
ml_pipeline_engine/dag/errors.py
ml_pipeline_engine/dag/graph.py
ml_pipeline_engine/dag/manager.py
ml_pipeline_engine/dag/storage.py
ml_pipeline_engine/dag_builders/__init__.py
ml_pipeline_engine/dag_builders/annotation/__init__.py
ml_pipeline_engine/dag_builders/annotation/builder.py
ml_pipeline_engine/dag_builders/annotation/errors.py
ml_pipeline_engine/dag_builders/annotation/marks.py
ml_pipeline_engine/events.py
ml_pipeline_engine/logs.py
ml_pipeline_engine/module_loading.py
ml_pipeline_engine/node/__init__.py
ml_pipeline_engine/node/base_nodes.py
ml_pipeline_engine/node/enums.py
ml_pipeline_engine/node/errors.py
ml_pipeline_engine/node/node.py
ml_pipeline_engine/node/retrying.py
ml_pipeline_engine/parallelism/__init__.py
ml_pipeline_engine/parallelism/basic.py
ml_pipeline_engine/parallelism/processes.py
ml_pipeline_engine/parallelism/threads.py
ml_pipeline_engine/types.py
ml_pipeline_viewer/.gitignore
ml_pipeline_viewer/__init__.py
ml_pipeline_viewer/cli.py
ml_pipeline_viewer/visualization/__init__.py
ml_pipeline_viewer/visualization/dag.py
ml_pipeline_viewer/visualization/sample.py
ml_pipeline_viewer/visualization/schema.py
ml_pipeline_viewer/visualization/utils.py
ml_pipeline_viewer/visualization/viewer/asset-manifest.json
ml_pipeline_viewer/visualization/viewer/favicon.ico
ml_pipeline_viewer/visualization/viewer/index.html
ml_pipeline_engine-2.3.2.dist-info/AUTHORS
ml_pipeline_engine-2.3.2.dist-info/LICENSE
ml_pipeline_engine-2.3.2.dist-info/METADATA
ml_pipeline_engine-2.3.2.dist-info/WHEEL
ml_pipeline_engine-2.3.2.dist-info/entry_points.txt
ml_pipeline_engine-2.3.2.dist-info/RECORD
