Metadata-Version: 2.3
Name: ml-pipeline-engine
Version: 2.3.2
Summary: Фреймворк для работы с пайплайном ML моделей
License: MIT
Author: Konyaev Matvey
Requires-Python: >=3.9,<3.14
Classifier: Development Status :: 5 - Production/Stable
Classifier: Intended Audience :: Developers
Classifier: License :: OSI Approved :: MIT License
Classifier: Programming Language :: Python :: 3
Classifier: Programming Language :: Python :: 3.9
Classifier: Programming Language :: Python :: 3.10
Classifier: Programming Language :: Python :: 3.11
Classifier: Programming Language :: Python :: 3.12
Classifier: Programming Language :: Python :: 3.13
Requires-Dist: anyio (>=4.9.0,<5.0.0)
Requires-Dist: cachetools (>=5.3.3,<6.0.0)
Requires-Dist: click (>=8.1.7,<9.0.0)
Requires-Dist: importlib-resources (>=6.4.0,<7.0.0)
Requires-Dist: networkx (>=3.1,<4.0)
Project-URL: Homepage, https://github.com/tochka-public/ml-pipeline-engine
Project-URL: Repository, https://github.com/tochka-public/ml-pipeline-engine
